{
  "name": "die-shrink",
  "version": "0.2.0",
  "title": "Die Shrink",
  "author": "The LORD thy GOD",
  "contact": "https://github.com/wcjohnson/die-shrink",
  "homepage": "https://github.com/wcjohnson/die-shrink",
  "description": "Create small, efficient circuit units containing many combinators.",
  "factorio_version": "2.1",
  "dependencies": [ "base >= 2.1.7", "0-things >= 0.3.1" ],
  "package": {
    "git_publish_branch": "main",
    "ignore": [ "crowdin.yml", "stylua.toml", "tests/**", "doc/**" ],
    "scripts": {
    },
    "sync_portal_details": true
  }
}
